vulscan/__init__.py
vulscan/__main__.py
vulscan/scanner.py
vulscan-0.3.dist-info/LICENSE.md
vulscan-0.3.dist-info/METADATA
vulscan-0.3.dist-info/WHEEL
vulscan-0.3.dist-info/entry_points.txt
vulscan-0.3.dist-info/top_level.txt
vulscan-0.3.dist-info/RECORD
