Metadata-Version: 2.2
Name: vulscan
Version: 0.3
Summary: A python library to scan your code for vulnerabilities.
Author: Aswin Venkat
Author-email: aspm@securin.io
Classifier: Programming Language :: Python :: 3
Classifier: License :: OSI Approved :: MIT License
Classifier: Operating System :: OS Independent
Requires-Python: >=3.6
License-File: LICENSE.md
Requires-Dist: requests>=2.32.3
Requires-Dist: boto3>=1.34.25
Requires-Dist: botocore>=1.34.25
Requires-Dist: pycryptodome>=3.10.1
Requires-Dist: toml>=0.10.2
Dynamic: author
Dynamic: author-email
Dynamic: classifier
Dynamic: description
Dynamic: description-content-type
Dynamic: requires-dist
Dynamic: requires-python
Dynamic: summary
